Metadata-Version: 1.0
Name: co-sa
Version: 0.1
Summary: Computer Optic Semantics
Home-page: UNKNOWN
Author: Alfredo Lozano
Author-email: lozanoa94@gmail.com
License: UNKNOWN
Platform: UNKNOWN
